posetf/__init__.py
posetf/pose_transformer.py
posetf-0.1.3.dist-info/LICENSE
posetf-0.1.3.dist-info/METADATA
posetf-0.1.3.dist-info/WHEEL
posetf-0.1.3.dist-info/top_level.txt
posetf-0.1.3.dist-info/RECORD
