Metadata-Version: 2.1
Name: posetf
Version: 0.1.3
Summary: Pose Transformer
Home-page: https://github.com/hiro-ya/PoseTransformer
Author: hiro-ya
Author-email: dev.hiro.ya@gmail.com
License: BSD 2-Clause License
Platform: UNKNOWN
Requires-Dist: pyquaternion
Requires-Dist: numpy
Provides-Extra: mqtt
Requires-Dist: paho-mqtt ; extra == 'mqtt'
